mcp_agents_mytool/__init__.py
mcp_agents_mytool/__main__.py
mcp_agents_mytool/mcp_tools_math.py
mcp_agents_mytool-0.1.4.dist-info/METADATA
mcp_agents_mytool-0.1.4.dist-info/WHEEL
mcp_agents_mytool-0.1.4.dist-info/entry_points.txt
mcp_agents_mytool-0.1.4.dist-info/RECORD
