Metadata-Version: 2.4
Name: mcp-agents-mytool
Version: 0.1.4
Summary: Add your description here
Author-email: Srinivas917 <srinivas1209pendela@gmail.com>
Requires-Python: >=3.11
Requires-Dist: httpx>=0.28.1
Requires-Dist: mcp[cli]>=1.12.3
Requires-Dist: numpy>=2.3.2
